<annotation>
  <folder>synthetic</folder>
  <filename>12157_62_5.jpg</filename>
  <path>/home/jk-pc/Desktop/ai_competition/synthetic/12157_62_5.jpg</path>
  <source>
    <database>Unknown</database>
  </source>
  <size>
    <width>388</width>
    <height>542</height>
    <depth>3</depth>
  </size>
  <segmented>0</segmented>
  <object>
    <name>Iris Scissors</name>
    <pose>Unspecified</pose>
    <truncated>0</truncated>
    <difficult>0</difficult>
    <bndbox>
      <xmin>154</xmin>
      <ymin>281</ymin>
      <xmax>308</xmax>
      <ymax>447</ymax>
    </bndbox>
  </object>
  <object>
    <name>Hook Surgical</name>
    <pose>Unspecified</pose>
    <truncated>0</truncated>
    <difficult>0</difficult>
    <bndbox>
      <xmin>67</xmin>
      <ymin>50</ymin>
      <xmax>214</xmax>
      <ymax>141</ymax>
    </bndbox>
  </object>
  <object>
    <name>Micro Scissor</name>
    <pose>Unspecified</pose>
    <truncated>0</truncated>
    <difficult>0</difficult>
    <bndbox>
      <xmin>175</xmin>
      <ymin>255</ymin>
      <xmax>358</xmax>
      <ymax>324</ymax>
    </bndbox>
  </object>
  <object>
    <name>Micro Scissor</name>
    <pose>Unspecified</pose>
    <truncated>0</truncated>
    <difficult>0</difficult>
    <bndbox>
      <xmin>23</xmin>
      <ymin>417</ymin>
      <xmax>218</xmax>
      <ymax>495</ymax>
    </bndbox>
  </object>
  <object>
    <name>Fixation Ring</name>
    <pose>Unspecified</pose>
    <truncated>0</truncated>
    <difficult>0</difficult>
    <bndbox>
      <xmin>97</xmin>
      <ymin>240</ymin>
      <xmax>323</xmax>
      <ymax>310</ymax>
    </bndbox>
  </object>
</annotation>
