<annotation>
  <folder>synthetic</folder>
  <filename>12396_82_6.jpg</filename>
  <path>/home/jk-pc/Desktop/ai_competition/synthetic/12396_82_6.jpg</path>
  <source>
    <database>Unknown</database>
  </source>
  <size>
    <width>524</width>
    <height>355</height>
    <depth>3</depth>
  </size>
  <segmented>0</segmented>
  <object>
    <name>Chopper</name>
    <pose>Unspecified</pose>
    <truncated>0</truncated>
    <difficult>0</difficult>
    <bndbox>
      <xmin>200</xmin>
      <ymin>9</ymin>
      <xmax>374</xmax>
      <ymax>171</ymax>
    </bndbox>
  </object>
  <object>
    <name>Micro Scissor</name>
    <pose>Unspecified</pose>
    <truncated>0</truncated>
    <difficult>0</difficult>
    <bndbox>
      <xmin>147</xmin>
      <ymin>52</ymin>
      <xmax>359</xmax>
      <ymax>181</ymax>
    </bndbox>
  </object>
  <object>
    <name>Pusher</name>
    <pose>Unspecified</pose>
    <truncated>0</truncated>
    <difficult>0</difficult>
    <bndbox>
      <xmin>384</xmin>
      <ymin>17</ymin>
      <xmax>452</xmax>
      <ymax>182</ymax>
    </bndbox>
  </object>
  <object>
    <name>Tissue Forceps</name>
    <pose>Unspecified</pose>
    <truncated>0</truncated>
    <difficult>0</difficult>
    <bndbox>
      <xmin>123</xmin>
      <ymin>185</ymin>
      <xmax>241</xmax>
      <ymax>344</ymax>
    </bndbox>
  </object>
  <object>
    <name>Hook Surgical</name>
    <pose>Unspecified</pose>
    <truncated>0</truncated>
    <difficult>0</difficult>
    <bndbox>
      <xmin>479</xmin>
      <ymin>112</ymin>
      <xmax>501</xmax>
      <ymax>233</ymax>
    </bndbox>
  </object>
  <object>
    <name>Spatula Surgical</name>
    <pose>Unspecified</pose>
    <truncated>0</truncated>
    <difficult>0</difficult>
    <bndbox>
      <xmin>112</xmin>
      <ymin>73</ymin>
      <xmax>302</xmax>
      <ymax>202</ymax>
    </bndbox>
  </object>
</annotation>
