<annotation>
  <folder>synthetic</folder>
  <filename>13500_60_7.jpg</filename>
  <path>/home/jk-pc/Desktop/ai_competition/synthetic/13500_60_7.jpg</path>
  <source>
    <database>Unknown</database>
  </source>
  <size>
    <width>518</width>
    <height>347</height>
    <depth>3</depth>
  </size>
  <segmented>0</segmented>
  <object>
    <name>Scalpel Handle</name>
    <pose>Unspecified</pose>
    <truncated>0</truncated>
    <difficult>0</difficult>
    <bndbox>
      <xmin>103</xmin>
      <ymin>196</ymin>
      <xmax>203</xmax>
      <ymax>333</ymax>
    </bndbox>
  </object>
  <object>
    <name>Needle Holder</name>
    <pose>Unspecified</pose>
    <truncated>0</truncated>
    <difficult>0</difficult>
    <bndbox>
      <xmin>102</xmin>
      <ymin>80</ymin>
      <xmax>196</xmax>
      <ymax>239</ymax>
    </bndbox>
  </object>
  <object>
    <name>Dressing Forceps</name>
    <pose>Unspecified</pose>
    <truncated>0</truncated>
    <difficult>0</difficult>
    <bndbox>
      <xmin>345</xmin>
      <ymin>176</ymin>
      <xmax>508</xmax>
      <ymax>270</ymax>
    </bndbox>
  </object>
  <object>
    <name>Handpiece</name>
    <pose>Unspecified</pose>
    <truncated>0</truncated>
    <difficult>0</difficult>
    <bndbox>
      <xmin>64</xmin>
      <ymin>45</ymin>
      <xmax>135</xmax>
      <ymax>143</ymax>
    </bndbox>
  </object>
  <object>
    <name>Handpiece</name>
    <pose>Unspecified</pose>
    <truncated>0</truncated>
    <difficult>0</difficult>
    <bndbox>
      <xmin>53</xmin>
      <ymin>256</ymin>
      <xmax>187</xmax>
      <ymax>287</ymax>
    </bndbox>
  </object>
  <object>
    <name>Cannula</name>
    <pose>Unspecified</pose>
    <truncated>0</truncated>
    <difficult>0</difficult>
    <bndbox>
      <xmin>19</xmin>
      <ymin>72</ymin>
      <xmax>188</xmax>
      <ymax>207</ymax>
    </bndbox>
  </object>
  <object>
    <name>Surgical Spoon</name>
    <pose>Unspecified</pose>
    <truncated>0</truncated>
    <difficult>0</difficult>
    <bndbox>
      <xmin>378</xmin>
      <ymin>140</ymin>
      <xmax>470</xmax>
      <ymax>302</ymax>
    </bndbox>
  </object>
</annotation>
