<annotation>
  <folder>synthetic</folder>
  <filename>17274_30_5.jpg</filename>
  <path>/home/jk-pc/Desktop/ai_competition/synthetic/17274_30_5.jpg</path>
  <source>
    <database>Unknown</database>
  </source>
  <size>
    <width>536</width>
    <height>373</height>
    <depth>3</depth>
  </size>
  <segmented>0</segmented>
  <object>
    <name>Dressing Forceps</name>
    <pose>Unspecified</pose>
    <truncated>0</truncated>
    <difficult>0</difficult>
    <bndbox>
      <xmin>332</xmin>
      <ymin>138</ymin>
      <xmax>517</xmax>
      <ymax>216</ymax>
    </bndbox>
  </object>
  <object>
    <name>Tissue Forceps</name>
    <pose>Unspecified</pose>
    <truncated>0</truncated>
    <difficult>0</difficult>
    <bndbox>
      <xmin>11</xmin>
      <ymin>93</ymin>
      <xmax>138</xmax>
      <ymax>214</ymax>
    </bndbox>
  </object>
  <object>
    <name>Dressing Forceps</name>
    <pose>Unspecified</pose>
    <truncated>0</truncated>
    <difficult>0</difficult>
    <bndbox>
      <xmin>76</xmin>
      <ymin>38</ymin>
      <xmax>299</xmax>
      <ymax>100</ymax>
    </bndbox>
  </object>
  <object>
    <name>Needle Holder</name>
    <pose>Unspecified</pose>
    <truncated>0</truncated>
    <difficult>0</difficult>
    <bndbox>
      <xmin>283</xmin>
      <ymin>136</ymin>
      <xmax>411</xmax>
      <ymax>202</ymax>
    </bndbox>
  </object>
  <object>
    <name>Scalpel Handle</name>
    <pose>Unspecified</pose>
    <truncated>0</truncated>
    <difficult>0</difficult>
    <bndbox>
      <xmin>324</xmin>
      <ymin>74</ymin>
      <xmax>473</xmax>
      <ymax>108</ymax>
    </bndbox>
  </object>
</annotation>
