<annotation>
  <folder>synthetic</folder>
  <filename>1783_9_4.jpg</filename>
  <path>/home/jk-pc/Desktop/ai_competition/synthetic/1783_9_4.jpg</path>
  <source>
    <database>Unknown</database>
  </source>
  <size>
    <width>524</width>
    <height>355</height>
    <depth>3</depth>
  </size>
  <segmented>0</segmented>
  <object>
    <name>Dressing Forceps</name>
    <pose>Unspecified</pose>
    <truncated>0</truncated>
    <difficult>0</difficult>
    <bndbox>
      <xmin>261</xmin>
      <ymin>108</ymin>
      <xmax>498</xmax>
      <ymax>298</ymax>
    </bndbox>
  </object>
  <object>
    <name>Dressing Forceps</name>
    <pose>Unspecified</pose>
    <truncated>0</truncated>
    <difficult>0</difficult>
    <bndbox>
      <xmin>13</xmin>
      <ymin>109</ymin>
      <xmax>145</xmax>
      <ymax>204</ymax>
    </bndbox>
  </object>
  <object>
    <name>Surgical Spoon</name>
    <pose>Unspecified</pose>
    <truncated>0</truncated>
    <difficult>0</difficult>
    <bndbox>
      <xmin>141</xmin>
      <ymin>36</ymin>
      <xmax>252</xmax>
      <ymax>224</ymax>
    </bndbox>
  </object>
  <object>
    <name>Speculum</name>
    <pose>Unspecified</pose>
    <truncated>0</truncated>
    <difficult>0</difficult>
    <bndbox>
      <xmin>113</xmin>
      <ymin>4</ymin>
      <xmax>317</xmax>
      <ymax>213</ymax>
    </bndbox>
  </object>
</annotation>
