<annotation>
  <folder>synthetic</folder>
  <filename>18722_67_6.jpg</filename>
  <path>/home/jk-pc/Desktop/ai_competition/synthetic/18722_67_6.jpg</path>
  <source>
    <database>Unknown</database>
  </source>
  <size>
    <width>518</width>
    <height>347</height>
    <depth>3</depth>
  </size>
  <segmented>0</segmented>
  <object>
    <name>Spatula Surgical</name>
    <pose>Unspecified</pose>
    <truncated>0</truncated>
    <difficult>0</difficult>
    <bndbox>
      <xmin>23</xmin>
      <ymin>54</ymin>
      <xmax>247</xmax>
      <ymax>279</ymax>
    </bndbox>
  </object>
  <object>
    <name>Iris Scissors</name>
    <pose>Unspecified</pose>
    <truncated>0</truncated>
    <difficult>0</difficult>
    <bndbox>
      <xmin>51</xmin>
      <ymin>79</ymin>
      <xmax>252</xmax>
      <ymax>257</ymax>
    </bndbox>
  </object>
  <object>
    <name>Fixation Ring</name>
    <pose>Unspecified</pose>
    <truncated>0</truncated>
    <difficult>0</difficult>
    <bndbox>
      <xmin>464</xmin>
      <ymin>119</ymin>
      <xmax>504</xmax>
      <ymax>302</ymax>
    </bndbox>
  </object>
  <object>
    <name>Surgical Spoon</name>
    <pose>Unspecified</pose>
    <truncated>0</truncated>
    <difficult>0</difficult>
    <bndbox>
      <xmin>172</xmin>
      <ymin>201</ymin>
      <xmax>294</xmax>
      <ymax>243</ymax>
    </bndbox>
  </object>
  <object>
    <name>Needle Holder</name>
    <pose>Unspecified</pose>
    <truncated>0</truncated>
    <difficult>0</difficult>
    <bndbox>
      <xmin>119</xmin>
      <ymin>39</ymin>
      <xmax>317</xmax>
      <ymax>140</ymax>
    </bndbox>
  </object>
  <object>
    <name>Cannula</name>
    <pose>Unspecified</pose>
    <truncated>0</truncated>
    <difficult>0</difficult>
    <bndbox>
      <xmin>38</xmin>
      <ymin>50</ymin>
      <xmax>139</xmax>
      <ymax>198</ymax>
    </bndbox>
  </object>
</annotation>
