<annotation>
  <folder>synthetic</folder>
  <filename>20909_37_6.jpg</filename>
  <path>/home/jk-pc/Desktop/ai_competition/synthetic/20909_37_6.jpg</path>
  <source>
    <database>Unknown</database>
  </source>
  <size>
    <width>512</width>
    <height>337</height>
    <depth>3</depth>
  </size>
  <segmented>0</segmented>
  <object>
    <name>Handpiece</name>
    <pose>Unspecified</pose>
    <truncated>0</truncated>
    <difficult>0</difficult>
    <bndbox>
      <xmin>154</xmin>
      <ymin>30</ymin>
      <xmax>288</xmax>
      <ymax>216</ymax>
    </bndbox>
  </object>
  <object>
    <name>Micro Scissor</name>
    <pose>Unspecified</pose>
    <truncated>0</truncated>
    <difficult>0</difficult>
    <bndbox>
      <xmin>47</xmin>
      <ymin>95</ymin>
      <xmax>281</xmax>
      <ymax>221</ymax>
    </bndbox>
  </object>
  <object>
    <name>Handpiece</name>
    <pose>Unspecified</pose>
    <truncated>0</truncated>
    <difficult>0</difficult>
    <bndbox>
      <xmin>121</xmin>
      <ymin>43</ymin>
      <xmax>372</xmax>
      <ymax>256</ymax>
    </bndbox>
  </object>
  <object>
    <name>Scalpel Handle</name>
    <pose>Unspecified</pose>
    <truncated>0</truncated>
    <difficult>0</difficult>
    <bndbox>
      <xmin>75</xmin>
      <ymin>269</ymin>
      <xmax>212</xmax>
      <ymax>299</ymax>
    </bndbox>
  </object>
  <object>
    <name>Fixation Ring</name>
    <pose>Unspecified</pose>
    <truncated>0</truncated>
    <difficult>0</difficult>
    <bndbox>
      <xmin>333</xmin>
      <ymin>15</ymin>
      <xmax>495</xmax>
      <ymax>221</ymax>
    </bndbox>
  </object>
  <object>
    <name>Pusher</name>
    <pose>Unspecified</pose>
    <truncated>0</truncated>
    <difficult>0</difficult>
    <bndbox>
      <xmin>110</xmin>
      <ymin>158</ymin>
      <xmax>166</xmax>
      <ymax>298</ymax>
    </bndbox>
  </object>
</annotation>
