<annotation>
  <folder>synthetic</folder>
  <filename>21208_98_4.jpg</filename>
  <path>/home/jk-pc/Desktop/ai_competition/synthetic/21208_98_4.jpg</path>
  <source>
    <database>Unknown</database>
  </source>
  <size>
    <width>518</width>
    <height>347</height>
    <depth>3</depth>
  </size>
  <segmented>0</segmented>
  <object>
    <name>Scalpel Handle</name>
    <pose>Unspecified</pose>
    <truncated>0</truncated>
    <difficult>0</difficult>
    <bndbox>
      <xmin>55</xmin>
      <ymin>28</ymin>
      <xmax>179</xmax>
      <ymax>187</ymax>
    </bndbox>
  </object>
  <object>
    <name>Dressing Forceps</name>
    <pose>Unspecified</pose>
    <truncated>0</truncated>
    <difficult>0</difficult>
    <bndbox>
      <xmin>315</xmin>
      <ymin>20</ymin>
      <xmax>470</xmax>
      <ymax>196</ymax>
    </bndbox>
  </object>
  <object>
    <name>Iris Scissors</name>
    <pose>Unspecified</pose>
    <truncated>0</truncated>
    <difficult>0</difficult>
    <bndbox>
      <xmin>197</xmin>
      <ymin>18</ymin>
      <xmax>321</xmax>
      <ymax>132</ymax>
    </bndbox>
  </object>
  <object>
    <name>Tissue Forceps</name>
    <pose>Unspecified</pose>
    <truncated>0</truncated>
    <difficult>0</difficult>
    <bndbox>
      <xmin>124</xmin>
      <ymin>156</ymin>
      <xmax>209</xmax>
      <ymax>303</ymax>
    </bndbox>
  </object>
</annotation>
