<annotation>
  <folder>synthetic</folder>
  <filename>22261_80_3.jpg</filename>
  <path>/home/jk-pc/Desktop/ai_competition/synthetic/22261_80_3.jpg</path>
  <source>
    <database>Unknown</database>
  </source>
  <size>
    <width>530</width>
    <height>365</height>
    <depth>3</depth>
  </size>
  <segmented>0</segmented>
  <object>
    <name>Hook Surgical</name>
    <pose>Unspecified</pose>
    <truncated>0</truncated>
    <difficult>0</difficult>
    <bndbox>
      <xmin>290</xmin>
      <ymin>17</ymin>
      <xmax>417</xmax>
      <ymax>151</ymax>
    </bndbox>
  </object>
  <object>
    <name>Hook Surgical</name>
    <pose>Unspecified</pose>
    <truncated>0</truncated>
    <difficult>0</difficult>
    <bndbox>
      <xmin>117</xmin>
      <ymin>126</ymin>
      <xmax>143</xmax>
      <ymax>255</ymax>
    </bndbox>
  </object>
  <object>
    <name>Hook Surgical</name>
    <pose>Unspecified</pose>
    <truncated>0</truncated>
    <difficult>0</difficult>
    <bndbox>
      <xmin>482</xmin>
      <ymin>160</ymin>
      <xmax>527</xmax>
      <ymax>303</ymax>
    </bndbox>
  </object>
</annotation>
