<annotation>
  <folder>synthetic</folder>
  <filename>23446_65_3.jpg</filename>
  <path>/home/jk-pc/Desktop/ai_competition/synthetic/23446_65_3.jpg</path>
  <source>
    <database>Unknown</database>
  </source>
  <size>
    <width>344</width>
    <height>512</height>
    <depth>3</depth>
  </size>
  <segmented>0</segmented>
  <object>
    <name>Pusher</name>
    <pose>Unspecified</pose>
    <truncated>0</truncated>
    <difficult>0</difficult>
    <bndbox>
      <xmin>116</xmin>
      <ymin>87</ymin>
      <xmax>332</xmax>
      <ymax>172</ymax>
    </bndbox>
  </object>
  <object>
    <name>Chopper</name>
    <pose>Unspecified</pose>
    <truncated>0</truncated>
    <difficult>0</difficult>
    <bndbox>
      <xmin>65</xmin>
      <ymin>218</ymin>
      <xmax>289</xmax>
      <ymax>338</ymax>
    </bndbox>
  </object>
  <object>
    <name>Spatula Surgical</name>
    <pose>Unspecified</pose>
    <truncated>0</truncated>
    <difficult>0</difficult>
    <bndbox>
      <xmin>149</xmin>
      <ymin>319</ymin>
      <xmax>256</xmax>
      <ymax>458</ymax>
    </bndbox>
  </object>
</annotation>
