<annotation>
  <folder>synthetic</folder>
  <filename>23617_66_3.jpg</filename>
  <path>/home/jk-pc/Desktop/ai_competition/synthetic/23617_66_3.jpg</path>
  <source>
    <database>Unknown</database>
  </source>
  <size>
    <width>372</width>
    <height>530</height>
    <depth>3</depth>
  </size>
  <segmented>0</segmented>
  <object>
    <name>Dressing Forceps</name>
    <pose>Unspecified</pose>
    <truncated>0</truncated>
    <difficult>0</difficult>
    <bndbox>
      <xmin>182</xmin>
      <ymin>268</ymin>
      <xmax>305</xmax>
      <ymax>305</ymax>
    </bndbox>
  </object>
  <object>
    <name>Handpiece</name>
    <pose>Unspecified</pose>
    <truncated>0</truncated>
    <difficult>0</difficult>
    <bndbox>
      <xmin>60</xmin>
      <ymin>350</ymin>
      <xmax>264</xmax>
      <ymax>399</ymax>
    </bndbox>
  </object>
  <object>
    <name>Fixation Ring</name>
    <pose>Unspecified</pose>
    <truncated>0</truncated>
    <difficult>0</difficult>
    <bndbox>
      <xmin>179</xmin>
      <ymin>249</ymin>
      <xmax>268</xmax>
      <ymax>430</ymax>
    </bndbox>
  </object>
</annotation>
