<annotation>
  <folder>synthetic</folder>
  <filename>23836_93_5.jpg</filename>
  <path>/home/jk-pc/Desktop/ai_competition/synthetic/23836_93_5.jpg</path>
  <source>
    <database>Unknown</database>
  </source>
  <size>
    <width>524</width>
    <height>355</height>
    <depth>3</depth>
  </size>
  <segmented>0</segmented>
  <object>
    <name>Handpiece</name>
    <pose>Unspecified</pose>
    <truncated>0</truncated>
    <difficult>0</difficult>
    <bndbox>
      <xmin>4</xmin>
      <ymin>38</ymin>
      <xmax>193</xmax>
      <ymax>182</ymax>
    </bndbox>
  </object>
  <object>
    <name>Tissue Forceps</name>
    <pose>Unspecified</pose>
    <truncated>0</truncated>
    <difficult>0</difficult>
    <bndbox>
      <xmin>219</xmin>
      <ymin>93</ymin>
      <xmax>264</xmax>
      <ymax>226</ymax>
    </bndbox>
  </object>
  <object>
    <name>Tissue Forceps</name>
    <pose>Unspecified</pose>
    <truncated>0</truncated>
    <difficult>0</difficult>
    <bndbox>
      <xmin>308</xmin>
      <ymin>124</ymin>
      <xmax>476</xmax>
      <ymax>338</ymax>
    </bndbox>
  </object>
  <object>
    <name>Hook Surgical</name>
    <pose>Unspecified</pose>
    <truncated>0</truncated>
    <difficult>0</difficult>
    <bndbox>
      <xmin>36</xmin>
      <ymin>35</ymin>
      <xmax>220</xmax>
      <ymax>190</ymax>
    </bndbox>
  </object>
  <object>
    <name>Scalpel Handle</name>
    <pose>Unspecified</pose>
    <truncated>0</truncated>
    <difficult>0</difficult>
    <bndbox>
      <xmin>321</xmin>
      <ymin>256</ymin>
      <xmax>463</xmax>
      <ymax>275</ymax>
    </bndbox>
  </object>
</annotation>
