<annotation>
  <folder>synthetic</folder>
  <filename>24481_97_4.jpg</filename>
  <path>/home/jk-pc/Desktop/ai_competition/synthetic/24481_97_4.jpg</path>
  <source>
    <database>Unknown</database>
  </source>
  <size>
    <width>536</width>
    <height>373</height>
    <depth>3</depth>
  </size>
  <segmented>0</segmented>
  <object>
    <name>Micro Scissor</name>
    <pose>Unspecified</pose>
    <truncated>0</truncated>
    <difficult>0</difficult>
    <bndbox>
      <xmin>117</xmin>
      <ymin>11</ymin>
      <xmax>200</xmax>
      <ymax>202</ymax>
    </bndbox>
  </object>
  <object>
    <name>Iris Scissors</name>
    <pose>Unspecified</pose>
    <truncated>0</truncated>
    <difficult>0</difficult>
    <bndbox>
      <xmin>341</xmin>
      <ymin>28</ymin>
      <xmax>517</xmax>
      <ymax>260</ymax>
    </bndbox>
  </object>
  <object>
    <name>Chopper</name>
    <pose>Unspecified</pose>
    <truncated>0</truncated>
    <difficult>0</difficult>
    <bndbox>
      <xmin>269</xmin>
      <ymin>83</ymin>
      <xmax>534</xmax>
      <ymax>310</ymax>
    </bndbox>
  </object>
  <object>
    <name>Handpiece</name>
    <pose>Unspecified</pose>
    <truncated>0</truncated>
    <difficult>0</difficult>
    <bndbox>
      <xmin>95</xmin>
      <ymin>74</ymin>
      <xmax>168</xmax>
      <ymax>279</ymax>
    </bndbox>
  </object>
</annotation>
