<annotation>
  <folder>synthetic</folder>
  <filename>24701_72_3.jpg</filename>
  <path>/home/jk-pc/Desktop/ai_competition/synthetic/24701_72_3.jpg</path>
  <source>
    <database>Unknown</database>
  </source>
  <size>
    <width>362</width>
    <height>524</height>
    <depth>3</depth>
  </size>
  <segmented>0</segmented>
  <object>
    <name>Iris Scissors</name>
    <pose>Unspecified</pose>
    <truncated>0</truncated>
    <difficult>0</difficult>
    <bndbox>
      <xmin>16</xmin>
      <ymin>328</ymin>
      <xmax>145</xmax>
      <ymax>402</ymax>
    </bndbox>
  </object>
  <object>
    <name>Iris Scissors</name>
    <pose>Unspecified</pose>
    <truncated>0</truncated>
    <difficult>0</difficult>
    <bndbox>
      <xmin>174</xmin>
      <ymin>212</ymin>
      <xmax>307</xmax>
      <ymax>322</ymax>
    </bndbox>
  </object>
  <object>
    <name>Spatula Surgical</name>
    <pose>Unspecified</pose>
    <truncated>0</truncated>
    <difficult>0</difficult>
    <bndbox>
      <xmin>135</xmin>
      <ymin>271</ymin>
      <xmax>336</xmax>
      <ymax>424</ymax>
    </bndbox>
  </object>
</annotation>
