<annotation>
  <folder>synthetic</folder>
  <filename>25475_33_3.jpg</filename>
  <path>/home/jk-pc/Desktop/ai_competition/synthetic/25475_33_3.jpg</path>
  <source>
    <database>Unknown</database>
  </source>
  <size>
    <width>518</width>
    <height>347</height>
    <depth>3</depth>
  </size>
  <segmented>0</segmented>
  <object>
    <name>Cannula</name>
    <pose>Unspecified</pose>
    <truncated>0</truncated>
    <difficult>0</difficult>
    <bndbox>
      <xmin>246</xmin>
      <ymin>97</ymin>
      <xmax>381</xmax>
      <ymax>335</ymax>
    </bndbox>
  </object>
  <object>
    <name>Fixation Ring</name>
    <pose>Unspecified</pose>
    <truncated>0</truncated>
    <difficult>0</difficult>
    <bndbox>
      <xmin>210</xmin>
      <ymin>161</ymin>
      <xmax>418</xmax>
      <ymax>235</ymax>
    </bndbox>
  </object>
  <object>
    <name>Tissue Forceps</name>
    <pose>Unspecified</pose>
    <truncated>0</truncated>
    <difficult>0</difficult>
    <bndbox>
      <xmin>141</xmin>
      <ymin>74</ymin>
      <xmax>257</xmax>
      <ymax>281</ymax>
    </bndbox>
  </object>
</annotation>
