<annotation>
  <folder>synthetic</folder>
  <filename>25749_50_6.jpg</filename>
  <path>/home/jk-pc/Desktop/ai_competition/synthetic/25749_50_6.jpg</path>
  <source>
    <database>Unknown</database>
  </source>
  <size>
    <width>380</width>
    <height>536</height>
    <depth>3</depth>
  </size>
  <segmented>0</segmented>
  <object>
    <name>Fixation Ring</name>
    <pose>Unspecified</pose>
    <truncated>0</truncated>
    <difficult>0</difficult>
    <bndbox>
      <xmin>142</xmin>
      <ymin>85</ymin>
      <xmax>301</xmax>
      <ymax>281</ymax>
    </bndbox>
  </object>
  <object>
    <name>Fixation Ring</name>
    <pose>Unspecified</pose>
    <truncated>0</truncated>
    <difficult>0</difficult>
    <bndbox>
      <xmin>104</xmin>
      <ymin>81</ymin>
      <xmax>264</xmax>
      <ymax>222</ymax>
    </bndbox>
  </object>
  <object>
    <name>Surgical Spoon</name>
    <pose>Unspecified</pose>
    <truncated>0</truncated>
    <difficult>0</difficult>
    <bndbox>
      <xmin>32</xmin>
      <ymin>377</ymin>
      <xmax>134</xmax>
      <ymax>479</ymax>
    </bndbox>
  </object>
  <object>
    <name>Hook Surgical</name>
    <pose>Unspecified</pose>
    <truncated>0</truncated>
    <difficult>0</difficult>
    <bndbox>
      <xmin>70</xmin>
      <ymin>37</ymin>
      <xmax>227</xmax>
      <ymax>72</ymax>
    </bndbox>
  </object>
  <object>
    <name>Pusher</name>
    <pose>Unspecified</pose>
    <truncated>0</truncated>
    <difficult>0</difficult>
    <bndbox>
      <xmin>106</xmin>
      <ymin>331</ymin>
      <xmax>342</xmax>
      <ymax>386</ymax>
    </bndbox>
  </object>
  <object>
    <name>Spatula Surgical</name>
    <pose>Unspecified</pose>
    <truncated>0</truncated>
    <difficult>0</difficult>
    <bndbox>
      <xmin>76</xmin>
      <ymin>216</ymin>
      <xmax>197</xmax>
      <ymax>233</ymax>
    </bndbox>
  </object>
</annotation>
