<annotation>
  <folder>synthetic</folder>
  <filename>25945_2_8.jpg</filename>
  <path>/home/jk-pc/Desktop/ai_competition/synthetic/25945_2_8.jpg</path>
  <source>
    <database>Unknown</database>
  </source>
  <size>
    <width>524</width>
    <height>355</height>
    <depth>3</depth>
  </size>
  <segmented>0</segmented>
  <object>
    <name>Iris Scissors</name>
    <pose>Unspecified</pose>
    <truncated>0</truncated>
    <difficult>0</difficult>
    <bndbox>
      <xmin>81</xmin>
      <ymin>63</ymin>
      <xmax>283</xmax>
      <ymax>283</ymax>
    </bndbox>
  </object>
  <object>
    <name>Iris Scissors</name>
    <pose>Unspecified</pose>
    <truncated>0</truncated>
    <difficult>0</difficult>
    <bndbox>
      <xmin>328</xmin>
      <ymin>202</ymin>
      <xmax>485</xmax>
      <ymax>333</ymax>
    </bndbox>
  </object>
  <object>
    <name>Tissue Forceps</name>
    <pose>Unspecified</pose>
    <truncated>0</truncated>
    <difficult>0</difficult>
    <bndbox>
      <xmin>140</xmin>
      <ymin>59</ymin>
      <xmax>298</xmax>
      <ymax>208</ymax>
    </bndbox>
  </object>
  <object>
    <name>Pusher</name>
    <pose>Unspecified</pose>
    <truncated>0</truncated>
    <difficult>0</difficult>
    <bndbox>
      <xmin>227</xmin>
      <ymin>191</ymin>
      <xmax>366</xmax>
      <ymax>258</ymax>
    </bndbox>
  </object>
  <object>
    <name>Tissue Forceps</name>
    <pose>Unspecified</pose>
    <truncated>0</truncated>
    <difficult>0</difficult>
    <bndbox>
      <xmin>169</xmin>
      <ymin>101</ymin>
      <xmax>322</xmax>
      <ymax>254</ymax>
    </bndbox>
  </object>
  <object>
    <name>Surgical Spoon</name>
    <pose>Unspecified</pose>
    <truncated>0</truncated>
    <difficult>0</difficult>
    <bndbox>
      <xmin>2</xmin>
      <ymin>25</ymin>
      <xmax>13</xmax>
      <ymax>167</ymax>
    </bndbox>
  </object>
  <object>
    <name>Spatula Surgical</name>
    <pose>Unspecified</pose>
    <truncated>0</truncated>
    <difficult>0</difficult>
    <bndbox>
      <xmin>255</xmin>
      <ymin>81</ymin>
      <xmax>409</xmax>
      <ymax>277</ymax>
    </bndbox>
  </object>
  <object>
    <name>Surgical Spoon</name>
    <pose>Unspecified</pose>
    <truncated>0</truncated>
    <difficult>0</difficult>
    <bndbox>
      <xmin>81</xmin>
      <ymin>193</ymin>
      <xmax>199</xmax>
      <ymax>250</ymax>
    </bndbox>
  </object>
</annotation>
