<annotation>
  <folder>synthetic</folder>
  <filename>26131_83_3.jpg</filename>
  <path>/home/jk-pc/Desktop/ai_competition/synthetic/26131_83_3.jpg</path>
  <source>
    <database>Unknown</database>
  </source>
  <size>
    <width>530</width>
    <height>365</height>
    <depth>3</depth>
  </size>
  <segmented>0</segmented>
  <object>
    <name>Scalpel Handle</name>
    <pose>Unspecified</pose>
    <truncated>0</truncated>
    <difficult>0</difficult>
    <bndbox>
      <xmin>14</xmin>
      <ymin>204</ymin>
      <xmax>209</xmax>
      <ymax>324</ymax>
    </bndbox>
  </object>
  <object>
    <name>Handpiece</name>
    <pose>Unspecified</pose>
    <truncated>0</truncated>
    <difficult>0</difficult>
    <bndbox>
      <xmin>276</xmin>
      <ymin>133</ymin>
      <xmax>411</xmax>
      <ymax>321</ymax>
    </bndbox>
  </object>
  <object>
    <name>Dressing Forceps</name>
    <pose>Unspecified</pose>
    <truncated>0</truncated>
    <difficult>0</difficult>
    <bndbox>
      <xmin>238</xmin>
      <ymin>107</ymin>
      <xmax>359</xmax>
      <ymax>263</ymax>
    </bndbox>
  </object>
</annotation>
