<annotation>
  <folder>synthetic</folder>
  <filename>2654_77_5.jpg</filename>
  <path>/home/jk-pc/Desktop/ai_competition/synthetic/2654_77_5.jpg</path>
  <source>
    <database>Unknown</database>
  </source>
  <size>
    <width>354</width>
    <height>518</height>
    <depth>3</depth>
  </size>
  <segmented>0</segmented>
  <object>
    <name>Tissue Forceps</name>
    <pose>Unspecified</pose>
    <truncated>0</truncated>
    <difficult>0</difficult>
    <bndbox>
      <xmin>26</xmin>
      <ymin>157</ymin>
      <xmax>183</xmax>
      <ymax>279</ymax>
    </bndbox>
  </object>
  <object>
    <name>Speculum</name>
    <pose>Unspecified</pose>
    <truncated>0</truncated>
    <difficult>0</difficult>
    <bndbox>
      <xmin>84</xmin>
      <ymin>246</ymin>
      <xmax>180</xmax>
      <ymax>376</ymax>
    </bndbox>
  </object>
  <object>
    <name>Spatula Surgical</name>
    <pose>Unspecified</pose>
    <truncated>0</truncated>
    <difficult>0</difficult>
    <bndbox>
      <xmin>216</xmin>
      <ymin>62</ymin>
      <xmax>351</xmax>
      <ymax>229</ymax>
    </bndbox>
  </object>
  <object>
    <name>Micro Scissor</name>
    <pose>Unspecified</pose>
    <truncated>0</truncated>
    <difficult>0</difficult>
    <bndbox>
      <xmin>15</xmin>
      <ymin>91</ymin>
      <xmax>237</xmax>
      <ymax>158</ymax>
    </bndbox>
  </object>
  <object>
    <name>Micro Scissor</name>
    <pose>Unspecified</pose>
    <truncated>0</truncated>
    <difficult>0</difficult>
    <bndbox>
      <xmin>102</xmin>
      <ymin>267</ymin>
      <xmax>277</xmax>
      <ymax>318</ymax>
    </bndbox>
  </object>
</annotation>
