<annotation>
  <folder>synthetic</folder>
  <filename>26573_53_4.jpg</filename>
  <path>/home/jk-pc/Desktop/ai_competition/synthetic/26573_53_4.jpg</path>
  <source>
    <database>Unknown</database>
  </source>
  <size>
    <width>518</width>
    <height>347</height>
    <depth>3</depth>
  </size>
  <segmented>0</segmented>
  <object>
    <name>Needle Holder</name>
    <pose>Unspecified</pose>
    <truncated>0</truncated>
    <difficult>0</difficult>
    <bndbox>
      <xmin>294</xmin>
      <ymin>158</ymin>
      <xmax>360</xmax>
      <ymax>318</ymax>
    </bndbox>
  </object>
  <object>
    <name>Hook Surgical</name>
    <pose>Unspecified</pose>
    <truncated>0</truncated>
    <difficult>0</difficult>
    <bndbox>
      <xmin>56</xmin>
      <ymin>16</ymin>
      <xmax>353</xmax>
      <ymax>313</ymax>
    </bndbox>
  </object>
  <object>
    <name>Needle Holder</name>
    <pose>Unspecified</pose>
    <truncated>0</truncated>
    <difficult>0</difficult>
    <bndbox>
      <xmin>405</xmin>
      <ymin>51</ymin>
      <xmax>484</xmax>
      <ymax>168</ymax>
    </bndbox>
  </object>
  <object>
    <name>Needle Holder</name>
    <pose>Unspecified</pose>
    <truncated>0</truncated>
    <difficult>0</difficult>
    <bndbox>
      <xmin>375</xmin>
      <ymin>211</ymin>
      <xmax>506</xmax>
      <ymax>279</ymax>
    </bndbox>
  </object>
</annotation>
