<annotation>
  <folder>synthetic</folder>
  <filename>27288_28_4.jpg</filename>
  <path>/home/jk-pc/Desktop/ai_competition/synthetic/27288_28_4.jpg</path>
  <source>
    <database>Unknown</database>
  </source>
  <size>
    <width>388</width>
    <height>542</height>
    <depth>3</depth>
  </size>
  <segmented>0</segmented>
  <object>
    <name>Tissue Forceps</name>
    <pose>Unspecified</pose>
    <truncated>0</truncated>
    <difficult>0</difficult>
    <bndbox>
      <xmin>5</xmin>
      <ymin>237</ymin>
      <xmax>221</xmax>
      <ymax>396</ymax>
    </bndbox>
  </object>
  <object>
    <name>Needle Holder</name>
    <pose>Unspecified</pose>
    <truncated>0</truncated>
    <difficult>0</difficult>
    <bndbox>
      <xmin>209</xmin>
      <ymin>238</ymin>
      <xmax>364</xmax>
      <ymax>369</ymax>
    </bndbox>
  </object>
  <object>
    <name>Needle Holder</name>
    <pose>Unspecified</pose>
    <truncated>0</truncated>
    <difficult>0</difficult>
    <bndbox>
      <xmin>73</xmin>
      <ymin>331</ymin>
      <xmax>244</xmax>
      <ymax>450</ymax>
    </bndbox>
  </object>
  <object>
    <name>Speculum</name>
    <pose>Unspecified</pose>
    <truncated>0</truncated>
    <difficult>0</difficult>
    <bndbox>
      <xmin>122</xmin>
      <ymin>59</ymin>
      <xmax>203</xmax>
      <ymax>191</ymax>
    </bndbox>
  </object>
</annotation>
