<annotation>
  <folder>synthetic</folder>
  <filename>28518_19_3.jpg</filename>
  <path>/home/jk-pc/Desktop/ai_competition/synthetic/28518_19_3.jpg</path>
  <source>
    <database>Unknown</database>
  </source>
  <size>
    <width>518</width>
    <height>347</height>
    <depth>3</depth>
  </size>
  <segmented>0</segmented>
  <object>
    <name>Pusher</name>
    <pose>Unspecified</pose>
    <truncated>0</truncated>
    <difficult>0</difficult>
    <bndbox>
      <xmin>322</xmin>
      <ymin>16</ymin>
      <xmax>429</xmax>
      <ymax>68</ymax>
    </bndbox>
  </object>
  <object>
    <name>Scalpel Handle</name>
    <pose>Unspecified</pose>
    <truncated>0</truncated>
    <difficult>0</difficult>
    <bndbox>
      <xmin>76</xmin>
      <ymin>250</ymin>
      <xmax>243</xmax>
      <ymax>299</ymax>
    </bndbox>
  </object>
  <object>
    <name>Spatula Surgical</name>
    <pose>Unspecified</pose>
    <truncated>0</truncated>
    <difficult>0</difficult>
    <bndbox>
      <xmin>328</xmin>
      <ymin>32</ymin>
      <xmax>465</xmax>
      <ymax>244</ymax>
    </bndbox>
  </object>
</annotation>
