<annotation>
  <folder>synthetic</folder>
  <filename>29003_67_4.jpg</filename>
  <path>/home/jk-pc/Desktop/ai_competition/synthetic/29003_67_4.jpg</path>
  <source>
    <database>Unknown</database>
  </source>
  <size>
    <width>518</width>
    <height>347</height>
    <depth>3</depth>
  </size>
  <segmented>0</segmented>
  <object>
    <name>Tissue Forceps</name>
    <pose>Unspecified</pose>
    <truncated>0</truncated>
    <difficult>0</difficult>
    <bndbox>
      <xmin>377</xmin>
      <ymin>74</ymin>
      <xmax>481</xmax>
      <ymax>254</ymax>
    </bndbox>
  </object>
  <object>
    <name>Hook Surgical</name>
    <pose>Unspecified</pose>
    <truncated>0</truncated>
    <difficult>0</difficult>
    <bndbox>
      <xmin>402</xmin>
      <ymin>171</ymin>
      <xmax>511</xmax>
      <ymax>322</ymax>
    </bndbox>
  </object>
  <object>
    <name>Speculum</name>
    <pose>Unspecified</pose>
    <truncated>0</truncated>
    <difficult>0</difficult>
    <bndbox>
      <xmin>48</xmin>
      <ymin>159</ymin>
      <xmax>289</xmax>
      <ymax>283</ymax>
    </bndbox>
  </object>
  <object>
    <name>Spatula Surgical</name>
    <pose>Unspecified</pose>
    <truncated>0</truncated>
    <difficult>0</difficult>
    <bndbox>
      <xmin>42</xmin>
      <ymin>170</ymin>
      <xmax>159</xmax>
      <ymax>303</ymax>
    </bndbox>
  </object>
</annotation>
