<annotation>
  <folder>synthetic</folder>
  <filename>29239_57_3.jpg</filename>
  <path>/home/jk-pc/Desktop/ai_competition/synthetic/29239_57_3.jpg</path>
  <source>
    <database>Unknown</database>
  </source>
  <size>
    <width>372</width>
    <height>530</height>
    <depth>3</depth>
  </size>
  <segmented>0</segmented>
  <object>
    <name>Scalpel Handle</name>
    <pose>Unspecified</pose>
    <truncated>0</truncated>
    <difficult>0</difficult>
    <bndbox>
      <xmin>110</xmin>
      <ymin>360</ymin>
      <xmax>171</xmax>
      <ymax>519</ymax>
    </bndbox>
  </object>
  <object>
    <name>Tissue Forceps</name>
    <pose>Unspecified</pose>
    <truncated>0</truncated>
    <difficult>0</difficult>
    <bndbox>
      <xmin>92</xmin>
      <ymin>91</ymin>
      <xmax>280</xmax>
      <ymax>249</ymax>
    </bndbox>
  </object>
  <object>
    <name>Needle Holder</name>
    <pose>Unspecified</pose>
    <truncated>0</truncated>
    <difficult>0</difficult>
    <bndbox>
      <xmin>19</xmin>
      <ymin>25</ymin>
      <xmax>185</xmax>
      <ymax>225</ymax>
    </bndbox>
  </object>
</annotation>
