<annotation>
  <folder>synthetic</folder>
  <filename>299_77_3.jpg</filename>
  <path>/home/jk-pc/Desktop/ai_competition/synthetic/299_77_3.jpg</path>
  <source>
    <database>Unknown</database>
  </source>
  <size>
    <width>354</width>
    <height>518</height>
    <depth>3</depth>
  </size>
  <segmented>0</segmented>
  <object>
    <name>Hook Surgical</name>
    <pose>Unspecified</pose>
    <truncated>0</truncated>
    <difficult>0</difficult>
    <bndbox>
      <xmin>79</xmin>
      <ymin>69</ymin>
      <xmax>190</xmax>
      <ymax>272</ymax>
    </bndbox>
  </object>
  <object>
    <name>Fixation Ring</name>
    <pose>Unspecified</pose>
    <truncated>0</truncated>
    <difficult>0</difficult>
    <bndbox>
      <xmin>319</xmin>
      <ymin>368</ymin>
      <xmax>348</xmax>
      <ymax>509</ymax>
    </bndbox>
  </object>
  <object>
    <name>Hook Surgical</name>
    <pose>Unspecified</pose>
    <truncated>0</truncated>
    <difficult>0</difficult>
    <bndbox>
      <xmin>6</xmin>
      <ymin>326</ymin>
      <xmax>246</xmax>
      <ymax>358</ymax>
    </bndbox>
  </object>
</annotation>
