<annotation>
  <folder>synthetic</folder>
  <filename>3166_65_3.jpg</filename>
  <path>/home/jk-pc/Desktop/ai_competition/synthetic/3166_65_3.jpg</path>
  <source>
    <database>Unknown</database>
  </source>
  <size>
    <width>344</width>
    <height>512</height>
    <depth>3</depth>
  </size>
  <segmented>0</segmented>
  <object>
    <name>Chopper</name>
    <pose>Unspecified</pose>
    <truncated>0</truncated>
    <difficult>0</difficult>
    <bndbox>
      <xmin>111</xmin>
      <ymin>144</ymin>
      <xmax>140</xmax>
      <ymax>271</ymax>
    </bndbox>
  </object>
  <object>
    <name>Iris Scissors</name>
    <pose>Unspecified</pose>
    <truncated>0</truncated>
    <difficult>0</difficult>
    <bndbox>
      <xmin>52</xmin>
      <ymin>40</ymin>
      <xmax>329</xmax>
      <ymax>317</ymax>
    </bndbox>
  </object>
  <object>
    <name>Iris Scissors</name>
    <pose>Unspecified</pose>
    <truncated>0</truncated>
    <difficult>0</difficult>
    <bndbox>
      <xmin>37</xmin>
      <ymin>200</ymin>
      <xmax>222</xmax>
      <ymax>439</ymax>
    </bndbox>
  </object>
</annotation>
