<annotation>
  <folder>synthetic</folder>
  <filename>3548_68_4.jpg</filename>
  <path>/home/jk-pc/Desktop/ai_competition/synthetic/3548_68_4.jpg</path>
  <source>
    <database>Unknown</database>
  </source>
  <size>
    <width>530</width>
    <height>365</height>
    <depth>3</depth>
  </size>
  <segmented>0</segmented>
  <object>
    <name>Speculum</name>
    <pose>Unspecified</pose>
    <truncated>0</truncated>
    <difficult>0</difficult>
    <bndbox>
      <xmin>69</xmin>
      <ymin>106</ymin>
      <xmax>207</xmax>
      <ymax>184</ymax>
    </bndbox>
  </object>
  <object>
    <name>Cannula</name>
    <pose>Unspecified</pose>
    <truncated>0</truncated>
    <difficult>0</difficult>
    <bndbox>
      <xmin>255</xmin>
      <ymin>91</ymin>
      <xmax>339</xmax>
      <ymax>231</ymax>
    </bndbox>
  </object>
  <object>
    <name>Spatula Surgical</name>
    <pose>Unspecified</pose>
    <truncated>0</truncated>
    <difficult>0</difficult>
    <bndbox>
      <xmin>183</xmin>
      <ymin>251</ymin>
      <xmax>240</xmax>
      <ymax>351</ymax>
    </bndbox>
  </object>
  <object>
    <name>Scalpel Handle</name>
    <pose>Unspecified</pose>
    <truncated>0</truncated>
    <difficult>0</difficult>
    <bndbox>
      <xmin>26</xmin>
      <ymin>109</ymin>
      <xmax>228</xmax>
      <ymax>192</ymax>
    </bndbox>
  </object>
</annotation>
