<annotation>
  <folder>synthetic</folder>
  <filename>4081_74_4.jpg</filename>
  <path>/home/jk-pc/Desktop/ai_competition/synthetic/4081_74_4.jpg</path>
  <source>
    <database>Unknown</database>
  </source>
  <size>
    <width>536</width>
    <height>373</height>
    <depth>3</depth>
  </size>
  <segmented>0</segmented>
  <object>
    <name>Cannula</name>
    <pose>Unspecified</pose>
    <truncated>0</truncated>
    <difficult>0</difficult>
    <bndbox>
      <xmin>385</xmin>
      <ymin>160</ymin>
      <xmax>502</xmax>
      <ymax>228</ymax>
    </bndbox>
  </object>
  <object>
    <name>Pusher</name>
    <pose>Unspecified</pose>
    <truncated>0</truncated>
    <difficult>0</difficult>
    <bndbox>
      <xmin>365</xmin>
      <ymin>125</ymin>
      <xmax>402</xmax>
      <ymax>235</ymax>
    </bndbox>
  </object>
  <object>
    <name>Needle Holder</name>
    <pose>Unspecified</pose>
    <truncated>0</truncated>
    <difficult>0</difficult>
    <bndbox>
      <xmin>58</xmin>
      <ymin>47</ymin>
      <xmax>276</xmax>
      <ymax>187</ymax>
    </bndbox>
  </object>
  <object>
    <name>Handpiece</name>
    <pose>Unspecified</pose>
    <truncated>0</truncated>
    <difficult>0</difficult>
    <bndbox>
      <xmin>239</xmin>
      <ymin>74</ymin>
      <xmax>398</xmax>
      <ymax>257</ymax>
    </bndbox>
  </object>
</annotation>
