<annotation>
  <folder>synthetic</folder>
  <filename>5101_31_3.jpg</filename>
  <path>/home/jk-pc/Desktop/ai_competition/synthetic/5101_31_3.jpg</path>
  <source>
    <database>Unknown</database>
  </source>
  <size>
    <width>540</width>
    <height>381</height>
    <depth>3</depth>
  </size>
  <segmented>0</segmented>
  <object>
    <name>Handpiece</name>
    <pose>Unspecified</pose>
    <truncated>0</truncated>
    <difficult>0</difficult>
    <bndbox>
      <xmin>170</xmin>
      <ymin>217</ymin>
      <xmax>315</xmax>
      <ymax>266</ymax>
    </bndbox>
  </object>
  <object>
    <name>Surgical Spoon</name>
    <pose>Unspecified</pose>
    <truncated>0</truncated>
    <difficult>0</difficult>
    <bndbox>
      <xmin>123</xmin>
      <ymin>44</ymin>
      <xmax>177</xmax>
      <ymax>220</ymax>
    </bndbox>
  </object>
  <object>
    <name>Scalpel Handle</name>
    <pose>Unspecified</pose>
    <truncated>0</truncated>
    <difficult>0</difficult>
    <bndbox>
      <xmin>346</xmin>
      <ymin>129</ymin>
      <xmax>374</xmax>
      <ymax>358</ymax>
    </bndbox>
  </object>
</annotation>
