<annotation>
  <folder>synthetic</folder>
  <filename>5624_36_4.jpg</filename>
  <path>/home/jk-pc/Desktop/ai_competition/synthetic/5624_36_4.jpg</path>
  <source>
    <database>Unknown</database>
  </source>
  <size>
    <width>518</width>
    <height>347</height>
    <depth>3</depth>
  </size>
  <segmented>0</segmented>
  <object>
    <name>Pusher</name>
    <pose>Unspecified</pose>
    <truncated>0</truncated>
    <difficult>0</difficult>
    <bndbox>
      <xmin>27</xmin>
      <ymin>73</ymin>
      <xmax>125</xmax>
      <ymax>167</ymax>
    </bndbox>
  </object>
  <object>
    <name>Surgical Spoon</name>
    <pose>Unspecified</pose>
    <truncated>0</truncated>
    <difficult>0</difficult>
    <bndbox>
      <xmin>259</xmin>
      <ymin>119</ymin>
      <xmax>402</xmax>
      <ymax>249</ymax>
    </bndbox>
  </object>
  <object>
    <name>Cannula</name>
    <pose>Unspecified</pose>
    <truncated>0</truncated>
    <difficult>0</difficult>
    <bndbox>
      <xmin>75</xmin>
      <ymin>90</ymin>
      <xmax>341</xmax>
      <ymax>319</ymax>
    </bndbox>
  </object>
  <object>
    <name>Pusher</name>
    <pose>Unspecified</pose>
    <truncated>0</truncated>
    <difficult>0</difficult>
    <bndbox>
      <xmin>285</xmin>
      <ymin>263</ymin>
      <xmax>450</xmax>
      <ymax>338</ymax>
    </bndbox>
  </object>
</annotation>
