<annotation>
  <folder>synthetic</folder>
  <filename>5744_99_4.jpg</filename>
  <path>/home/jk-pc/Desktop/ai_competition/synthetic/5744_99_4.jpg</path>
  <source>
    <database>Unknown</database>
  </source>
  <size>
    <width>540</width>
    <height>381</height>
    <depth>3</depth>
  </size>
  <segmented>0</segmented>
  <object>
    <name>Chopper</name>
    <pose>Unspecified</pose>
    <truncated>0</truncated>
    <difficult>0</difficult>
    <bndbox>
      <xmin>355</xmin>
      <ymin>75</ymin>
      <xmax>482</xmax>
      <ymax>96</ymax>
    </bndbox>
  </object>
  <object>
    <name>Tissue Forceps</name>
    <pose>Unspecified</pose>
    <truncated>0</truncated>
    <difficult>0</difficult>
    <bndbox>
      <xmin>348</xmin>
      <ymin>5</ymin>
      <xmax>459</xmax>
      <ymax>163</ymax>
    </bndbox>
  </object>
  <object>
    <name>Scalpel Handle</name>
    <pose>Unspecified</pose>
    <truncated>0</truncated>
    <difficult>0</difficult>
    <bndbox>
      <xmin>33</xmin>
      <ymin>183</ymin>
      <xmax>182</xmax>
      <ymax>375</ymax>
    </bndbox>
  </object>
  <object>
    <name>Hook Surgical</name>
    <pose>Unspecified</pose>
    <truncated>0</truncated>
    <difficult>0</difficult>
    <bndbox>
      <xmin>83</xmin>
      <ymin>202</ymin>
      <xmax>291</xmax>
      <ymax>341</ymax>
    </bndbox>
  </object>
</annotation>
