<annotation>
  <folder>synthetic</folder>
  <filename>5774_89_3.jpg</filename>
  <path>/home/jk-pc/Desktop/ai_competition/synthetic/5774_89_3.jpg</path>
  <source>
    <database>Unknown</database>
  </source>
  <size>
    <width>524</width>
    <height>355</height>
    <depth>3</depth>
  </size>
  <segmented>0</segmented>
  <object>
    <name>Dressing Forceps</name>
    <pose>Unspecified</pose>
    <truncated>0</truncated>
    <difficult>0</difficult>
    <bndbox>
      <xmin>55</xmin>
      <ymin>44</ymin>
      <xmax>138</xmax>
      <ymax>273</ymax>
    </bndbox>
  </object>
  <object>
    <name>Spatula Surgical</name>
    <pose>Unspecified</pose>
    <truncated>0</truncated>
    <difficult>0</difficult>
    <bndbox>
      <xmin>239</xmin>
      <ymin>52</ymin>
      <xmax>342</xmax>
      <ymax>138</ymax>
    </bndbox>
  </object>
  <object>
    <name>Surgical Spoon</name>
    <pose>Unspecified</pose>
    <truncated>0</truncated>
    <difficult>0</difficult>
    <bndbox>
      <xmin>206</xmin>
      <ymin>111</ymin>
      <xmax>360</xmax>
      <ymax>246</ymax>
    </bndbox>
  </object>
</annotation>
