<annotation>
  <folder>synthetic</folder>
  <filename>596_24_3.jpg</filename>
  <path>/home/jk-pc/Desktop/ai_competition/synthetic/596_24_3.jpg</path>
  <source>
    <database>Unknown</database>
  </source>
  <size>
    <width>518</width>
    <height>347</height>
    <depth>3</depth>
  </size>
  <segmented>0</segmented>
  <object>
    <name>Spatula Surgical</name>
    <pose>Unspecified</pose>
    <truncated>0</truncated>
    <difficult>0</difficult>
    <bndbox>
      <xmin>186</xmin>
      <ymin>102</ymin>
      <xmax>348</xmax>
      <ymax>264</ymax>
    </bndbox>
  </object>
  <object>
    <name>Micro Scissor</name>
    <pose>Unspecified</pose>
    <truncated>0</truncated>
    <difficult>0</difficult>
    <bndbox>
      <xmin>185</xmin>
      <ymin>45</ymin>
      <xmax>422</xmax>
      <ymax>204</ymax>
    </bndbox>
  </object>
  <object>
    <name>Fixation Ring</name>
    <pose>Unspecified</pose>
    <truncated>0</truncated>
    <difficult>0</difficult>
    <bndbox>
      <xmin>83</xmin>
      <ymin>268</ymin>
      <xmax>195</xmax>
      <ymax>341</ymax>
    </bndbox>
  </object>
</annotation>
