<annotation>
  <folder>synthetic</folder>
  <filename>6723_31_6.jpg</filename>
  <path>/home/jk-pc/Desktop/ai_competition/synthetic/6723_31_6.jpg</path>
  <source>
    <database>Unknown</database>
  </source>
  <size>
    <width>540</width>
    <height>381</height>
    <depth>3</depth>
  </size>
  <segmented>0</segmented>
  <object>
    <name>Hook Surgical</name>
    <pose>Unspecified</pose>
    <truncated>0</truncated>
    <difficult>0</difficult>
    <bndbox>
      <xmin>227</xmin>
      <ymin>145</ymin>
      <xmax>312</xmax>
      <ymax>313</ymax>
    </bndbox>
  </object>
  <object>
    <name>Pusher</name>
    <pose>Unspecified</pose>
    <truncated>0</truncated>
    <difficult>0</difficult>
    <bndbox>
      <xmin>254</xmin>
      <ymin>211</ymin>
      <xmax>282</xmax>
      <ymax>367</ymax>
    </bndbox>
  </object>
  <object>
    <name>Dressing Forceps</name>
    <pose>Unspecified</pose>
    <truncated>0</truncated>
    <difficult>0</difficult>
    <bndbox>
      <xmin>413</xmin>
      <ymin>192</ymin>
      <xmax>538</xmax>
      <ymax>303</ymax>
    </bndbox>
  </object>
  <object>
    <name>Needle Holder</name>
    <pose>Unspecified</pose>
    <truncated>0</truncated>
    <difficult>0</difficult>
    <bndbox>
      <xmin>198</xmin>
      <ymin>233</ymin>
      <xmax>402</xmax>
      <ymax>343</ymax>
    </bndbox>
  </object>
  <object>
    <name>Hook Surgical</name>
    <pose>Unspecified</pose>
    <truncated>0</truncated>
    <difficult>0</difficult>
    <bndbox>
      <xmin>300</xmin>
      <ymin>254</ymin>
      <xmax>364</xmax>
      <ymax>371</ymax>
    </bndbox>
  </object>
  <object>
    <name>Surgical Spoon</name>
    <pose>Unspecified</pose>
    <truncated>0</truncated>
    <difficult>0</difficult>
    <bndbox>
      <xmin>287</xmin>
      <ymin>200</ymin>
      <xmax>504</xmax>
      <ymax>256</ymax>
    </bndbox>
  </object>
</annotation>
