<annotation>
  <folder>synthetic</folder>
  <filename>825_35_5.jpg</filename>
  <path>/home/jk-pc/Desktop/ai_competition/synthetic/825_35_5.jpg</path>
  <source>
    <database>Unknown</database>
  </source>
  <size>
    <width>540</width>
    <height>381</height>
    <depth>3</depth>
  </size>
  <segmented>0</segmented>
  <object>
    <name>Chopper</name>
    <pose>Unspecified</pose>
    <truncated>0</truncated>
    <difficult>0</difficult>
    <bndbox>
      <xmin>209</xmin>
      <ymin>116</ymin>
      <xmax>354</xmax>
      <ymax>265</ymax>
    </bndbox>
  </object>
  <object>
    <name>Iris Scissors</name>
    <pose>Unspecified</pose>
    <truncated>0</truncated>
    <difficult>0</difficult>
    <bndbox>
      <xmin>356</xmin>
      <ymin>82</ymin>
      <xmax>514</xmax>
      <ymax>295</ymax>
    </bndbox>
  </object>
  <object>
    <name>Pusher</name>
    <pose>Unspecified</pose>
    <truncated>0</truncated>
    <difficult>0</difficult>
    <bndbox>
      <xmin>214</xmin>
      <ymin>51</ymin>
      <xmax>349</xmax>
      <ymax>58</ymax>
    </bndbox>
  </object>
  <object>
    <name>Micro Scissor</name>
    <pose>Unspecified</pose>
    <truncated>0</truncated>
    <difficult>0</difficult>
    <bndbox>
      <xmin>83</xmin>
      <ymin>95</ymin>
      <xmax>256</xmax>
      <ymax>182</ymax>
    </bndbox>
  </object>
  <object>
    <name>Dressing Forceps</name>
    <pose>Unspecified</pose>
    <truncated>0</truncated>
    <difficult>0</difficult>
    <bndbox>
      <xmin>384</xmin>
      <ymin>192</ymin>
      <xmax>522</xmax>
      <ymax>268</ymax>
    </bndbox>
  </object>
</annotation>
