<annotation>
  <folder>synthetic</folder>
  <filename>8469_88_3.jpg</filename>
  <path>/home/jk-pc/Desktop/ai_competition/synthetic/8469_88_3.jpg</path>
  <source>
    <database>Unknown</database>
  </source>
  <size>
    <width>388</width>
    <height>542</height>
    <depth>3</depth>
  </size>
  <segmented>0</segmented>
  <object>
    <name>Iris Scissors</name>
    <pose>Unspecified</pose>
    <truncated>0</truncated>
    <difficult>0</difficult>
    <bndbox>
      <xmin>41</xmin>
      <ymin>252</ymin>
      <xmax>153</xmax>
      <ymax>397</ymax>
    </bndbox>
  </object>
  <object>
    <name>Scalpel Handle</name>
    <pose>Unspecified</pose>
    <truncated>0</truncated>
    <difficult>0</difficult>
    <bndbox>
      <xmin>252</xmin>
      <ymin>136</ymin>
      <xmax>277</xmax>
      <ymax>287</ymax>
    </bndbox>
  </object>
  <object>
    <name>Pusher</name>
    <pose>Unspecified</pose>
    <truncated>0</truncated>
    <difficult>0</difficult>
    <bndbox>
      <xmin>31</xmin>
      <ymin>390</ymin>
      <xmax>235</xmax>
      <ymax>461</ymax>
    </bndbox>
  </object>
</annotation>
